chronos/__init__.py
chronos/base_timer.py
chronos/batch_timer.py
chronos/debug_timer.py
chronos/distributed_timer.py
chronos/timer.py
chronos/visual_timer.py
chronos_context_timer-1.0.0.dist-info/LICENSE
chronos_context_timer-1.0.0.dist-info/METADATA
chronos_context_timer-1.0.0.dist-info/WHEEL
chronos_context_timer-1.0.0.dist-info/top_level.txt
chronos_context_timer-1.0.0.dist-info/RECORD
