Metadata-Version: 2.1
Name: chronos-context-timer
Version: 1.0.0
Summary: Chronos: A Python library for advanced task timing with features like distributed timing, batch timing, real-time visualization, and debugging-friendly timers.
Home-page: https://github.com/adambirds/chronos
Author: Adam Birds
Author-email: adam.birds@adbwebdesigns.co.uk
License: LGPLv3
Project-URL: Bug Tracker, https://github.com/adambirds/chronos/issues
Classifier: License :: OSI Approved :: MIT License
Classifier: Programming Language :: Python
Classifier: Programming Language :: Python :: 3
Classifier: Programming Language :: Python :: 3.9
Classifier: Programming Language :: Python :: 3.10
Classifier: Programming Language :: Python :: 3.11
Classifier: Programming Language :: Python :: 3.12
Classifier: Operating System :: OS Independent
Requires-Python: >=3.6
License-File: LICENSE
